{
  "display": {
    "icon": { "id": "minecraft:blue_ice" },
    "title": { "text": "Nifl Requirement", "color": "gold" },
    "description": { "text": "Obtain blue or packed ice." },
    "frame": "task",
    "show_toast": false,
    "announce_to_chat": false,
    "hidden": true
  },
  "parent": "cobblemon_initiative:root",
  "criteria": { "requirement": { "trigger": "minecraft:inventory_changed", "conditions": { "items": [ { "items": [ "minecraft:blue_ice", "minecraft:packed_ice" ] } ] } } },
  "rewards": { "function": "cobblemon_initiative:flavor/mc/mc_gym9_ice" }
}
