{
  "defaultShop": [
    {
      "Poké Balls": [
        {
          "item": "cobblemon:poke_ball",
          "price": 2400
        },
        {
          "item": "cobblemon:premier_ball",
          "price": 2400
        },
        {
          "item": "cobblemon:great_ball",
          "price": 7200
        },
        {
          "item": "cobblemon:net_ball",
          "price": 12000
        },
        {
          "item": "cobblemon:nest_ball",
          "price": 12000
        },
        {
          "item": "cobblemon:ultra_ball",
          "price": 9600
        },
        {
          "item": "cobblemon:dusk_ball",
          "price": 12000
        },
        {
          "item": "cobblemon:quick_ball",
          "price": 12000
        },
        {
          "item": "cobblemon:timer_ball",
          "price": 12000
        },
        {
          "item": "cobblemon:repeat_ball",
          "price": 12000
        },
        {
          "item": "cobblemon:dive_ball",
          "price": 12000
        }
      ]
    },
    {
      "Medicine": [
        {
          "item": "cobblemon:potion",
          "price": 360
        },
        {
          "item": "cobblemon:super_potion",
          "price": 840
        },
        {
          "item": "cobblemon:hyper_potion",
          "price": 1800
        },
        {
          "item": "cobblemon:antidote",
          "price": 300
        },
        {
          "item": "cobblemon:paralyze_heal",
          "price": 300
        },
        {
          "item": "cobblemon:full_heal",
          "price": 1100
        }
      ]
    },
    {
      "Exp": [
        {
          "item": "cobblemon:exp_candy_xs",
          "price": 600
        },
        {
          "item": "cobblemon:exp_candy_s",
          "price": 4800
        },
        {
          "item": "cobblemon:exp_candy_m",
          "price": 18000
        }
      ]
    }
  ]
}
