{
  "name": "L§kaaaaa",
  "identity": "lauren",
  "ai": {
    "type": "rct",
    "data": {
      "maxSelectMargin": 0.15
    }
  },
  "battleFormat": "GEN_9_SINGLES",
  "bag": [
    {
      "item": "cobblemon:max_potion",
      "quantity": 2
    }
  ],
  "team": [
    {
      "species": "chansey",
      "gender": "FEMALE",
      "level": 81,
      "nature": "bold",
      "ability": "naturalcure",
      "moveset": [
        "seismictoss",
        "softboiled",
        "toxic",
        "healbell"
      ],
      "ivs": {
        "hp": 26,
        "atk": 26,
        "def": 26,
        "spa": 26,
        "spd": 26,
        "spe": 26
      },
      "evs": {
        "def": 200,
        "spd": 100
      },
      "heldItem": "cobblemon:eviolite"
    },
    {
      "species": "florges",
      "gender": "FEMALE",
      "level": 82,
      "nature": "calm",
      "ability": "flowerveil",
      "moveset": [
        "moonblast",
        "psychic",
        "wish",
        "calmmind"
      ],
      "ivs": {
        "hp": 26,
        "atk": 26,
        "def": 26,
        "spa": 26,
        "spd": 26,
        "spe": 26
      },
      "evs": {
        "hp": 200,
        "spd": 100
      },
      "heldItem": "cobblemon:leftovers"
    },
    {
      "species": "clefable",
      "gender": "FEMALE",
      "level": 83,
      "nature": "calm",
      "ability": "unaware",
      "moveset": [
        "moonblast",
        "moonlight",
        "calmmind",
        "flamethrower"
      ],
      "ivs": {
        "hp": 26,
        "atk": 26,
        "def": 26,
        "spa": 26,
        "spd": 26,
        "spe": 26
      },
      "evs": {
        "hp": 200,
        "spa": 100
      },
      "heldItem": "cobblemon:leftovers"
    },
    {
      "species": "snorlax",
      "gender": "MALE",
      "level": 84,
      "nature": "careful",
      "ability": "thickfat",
      "moveset": [
        "bodyslam",
        "earthquake",
        "curse",
        "rest"
      ],
      "ivs": {
        "hp": 26,
        "atk": 26,
        "def": 26,
        "spa": 26,
        "spd": 26,
        "spe": 26
      },
      "evs": {
        "hp": 150,
        "spd": 150
      },
      "heldItem": "cobblemon:sitrus_berry"
    },
    {
      "species": "togekiss",
      "gender": "FEMALE",
      "level": 85,
      "nature": "bold",
      "ability": "serenegrace",
      "moveset": [
        "airslash",
        "dazzlinggleam",
        "thunderwave",
        "roost"
      ],
      "ivs": {
        "hp": 26,
        "atk": 26,
        "def": 26,
        "spa": 26,
        "spd": 26,
        "spe": 26
      },
      "evs": {
        "hp": 200,
        "def": 100
      },
      "heldItem": "cobblemon:rocky_helmet"
    },
    {
      "species": "porygonz",
      "gender": "GENDERLESS",
      "level": 86,
      "nature": "modest",
      "ability": "adaptability",
      "moveset": [
        "triattack",
        "shadowball",
        "nastyplot",
        "recover"
      ],
      "ivs": {
        "hp": 26,
        "atk": 26,
        "def": 26,
        "spa": 26,
        "spd": 26,
        "spe": 26
      },
      "evs": {
        "hp": 100,
        "spa": 200
      },
      "heldItem": "cobblemon:life_orb"
    }
  ]
}
