[
  {
    "id": "fire_shrine_cultist_1",
    "name": "Fire Cultist",
    "displayName": "Flame Acolyte Pyra",
    "category": "shrine",
    "location": "Fire Shrine",
    "coordinates": [
      3500,
      51,
      4702
    ],
    "trainerType": "cultist",
    "prerequisites": [
      "royal_champion"
    ],
    "achievementOnDefeat": null,
    "rewards": [
      {
        "type": "item",
        "item": "cobblemon:ultra_ball",
        "count": 3
      }
    ],
    "battleFormat": "GEN_9_SINGLES",
    "ai": {
      "type": "rct",
      "data": {
        "maxSelectMargin": 0.2
      }
    },
    "bag": [
      {
        "item": "cobblemon:hyper_potion",
        "quantity": 2
      }
    ],
    "team": {
      "pokemon": [
        {
          "species": "cobblemon:flareon",
          "level": 75,
          "gender": "FEMALE",
          "nature": "adamant",
          "ability": "flashfire",
          "moveset": [
            "flareblitz",
            "superpower",
            "quickattack",
            "willowisp"
          ],
          "ivs": {
            "hp": 25,
            "atk": 25,
            "def": 25,
            "spa": 25,
            "spd": 25,
            "spe": 25
          },
          "evs": {
            "atk": 200,
            "spe": 100
          }
        },
        {
          "species": "cobblemon:rapidash",
          "level": 75,
          "gender": "MALE",
          "nature": "jolly",
          "ability": "flashfire",
          "moveset": [
            "flareblitz",
            "wildcharge",
            "highhorsepower",
            "morningsun"
          ],
          "ivs": {
            "hp": 25,
            "atk": 25,
            "def": 25,
            "spa": 25,
            "spd": 25,
            "spe": 25
          },
          "evs": {
            "atk": 200,
            "spe": 100
          }
        }
      ]
    }
  },
  {
    "id": "fire_shrine_cultist_2",
    "name": "Fire Cultist",
    "displayName": "Flame Zealot Cinder",
    "category": "shrine",
    "location": "Fire Shrine",
    "coordinates": [
      3503,
      51,
      4705
    ],
    "trainerType": "cultist",
    "prerequisites": [
      "royal_champion"
    ],
    "achievementOnDefeat": null,
    "rewards": [
      {
        "type": "item",
        "item": "cobblemon:ultra_ball",
        "count": 3
      }
    ],
    "battleFormat": "GEN_9_SINGLES",
    "ai": {
      "type": "rct",
      "data": {
        "maxSelectMargin": 0.2
      }
    },
    "bag": [
      {
        "item": "cobblemon:hyper_potion",
        "quantity": 2
      }
    ],
    "team": {
      "pokemon": [
        {
          "species": "cobblemon:blaziken",
          "level": 77,
          "gender": "MALE",
          "nature": "adamant",
          "ability": "speedboost",
          "moveset": [
            "flareblitz",
            "highjumpkick",
            "swordsdance",
            "protect"
          ],
          "ivs": {
            "hp": 28,
            "atk": 28,
            "def": 28,
            "spa": 28,
            "spd": 28,
            "spe": 28
          },
          "evs": {
            "atk": 252,
            "spe": 252
          }
        },
        {
          "species": "cobblemon:infernape",
          "level": 77,
          "gender": "MALE",
          "nature": "jolly",
          "ability": "ironist",
          "moveset": [
            "flareblitz",
            "closecombat",
            "uturn",
            "machpunch"
          ],
          "ivs": {
            "hp": 28,
            "atk": 28,
            "def": 28,
            "spa": 28,
            "spd": 28,
            "spe": 28
          },
          "evs": {
            "atk": 252,
            "spe": 252
          }
        },
        {
          "species": "cobblemon:chandelure",
          "level": 76,
          "gender": "FEMALE",
          "nature": "timid",
          "ability": "flashfire",
          "moveset": [
            "fireblast",
            "shadowball",
            "energyball",
            "trick"
          ],
          "ivs": {
            "hp": 28,
            "atk": 28,
            "def": 28,
            "spa": 28,
            "spd": 28,
            "spe": 28
          },
          "evs": {
            "spa": 252,
            "spe": 252
          }
        }
      ]
    }
  },
  {
    "id": "fire_shrine_leader",
    "name": "Fire Cult Leader",
    "displayName": "High Priest Ignis",
    "category": "shrine",
    "location": "Fire Shrine",
    "coordinates": [
      3510,
      51,
      4702
    ],
    "trainerType": "cult_leader",
    "prerequisites": [
      "fire_shrine_cultist_1",
      "fire_shrine_cultist_2"
    ],
    "achievementOnDefeat": "fire_shrine_complete",
    "rewards": [
      {
        "type": "item",
        "item": "cobblemon-initiative:fire_shrine_crystal",
        "count": 1
      },
      {
        "type": "item",
        "item": "cobblemon:master_ball",
        "count": 1
      },
      {
        "type": "item",
        "item": "minecraft:netherite_ingot",
        "count": 1
      }
    ],
    "battleFormat": "GEN_9_SINGLES",
    "ai": {
      "type": "rct",
      "data": {
        "maxSelectMargin": 0.1
      }
    },
    "bag": [
      {
        "item": "cobblemon:full_restore",
        "quantity": 3
      }
    ],
    "team": {
      "pokemon": [
        {
          "species": "cobblemon:volcarona",
          "level": 80,
          "gender": "FEMALE",
          "nature": "timid",
          "ability": "flamebody",
          "moveset": [
            "fierydance",
            "bugbuzz",
            "quiverdance",
            "gigadrain"
          ],
          "ivs": {
            "hp": 31,
            "atk": 31,
            "def": 31,
            "spa": 31,
            "spd": 31,
            "spe": 31
          },
          "evs": {
            "spa": 252,
            "spe": 252
          },
          "heldItem": "cobblemon:life_orb"
        },
        {
          "species": "cobblemon:arcanine",
          "level": 80,
          "gender": "MALE",
          "nature": "adamant",
          "ability": "intimidate",
          "moveset": [
            "flareblitz",
            "extremespeed",
            "wildcharge",
            "closecombat"
          ],
          "ivs": {
            "hp": 31,
            "atk": 31,
            "def": 31,
            "spa": 31,
            "spd": 31,
            "spe": 31
          },
          "evs": {
            "atk": 252,
            "spe": 252
          },
          "heldItem": "cobblemon:choice_band"
        },
        {
          "species": "cobblemon:charizard",
          "level": 82,
          "gender": "MALE",
          "nature": "timid",
          "ability": "solarpower",
          "moveset": [
            "fireblast",
            "airslash",
            "solarbeam",
            "focusblast"
          ],
          "ivs": {
            "hp": 31,
            "atk": 31,
            "def": 31,
            "spa": 31,
            "spd": 31,
            "spe": 31
          },
          "evs": {
            "spa": 252,
            "spe": 252
          },
          "heldItem": "cobblemon:choice_specs"
        },
        {
          "species": "cobblemon:heatran",
          "level": 82,
          "gender": "MALE",
          "nature": "modest",
          "ability": "flashfire",
          "moveset": [
            "magmastorm",
            "earthpower",
            "flashcannon",
            "stealthrock"
          ],
          "ivs": {
            "hp": 31,
            "atk": 31,
            "def": 31,
            "spa": 31,
            "spd": 31,
            "spe": 31
          },
          "evs": {
            "spa": 252,
            "hp": 252
          },
          "heldItem": "cobblemon:leftovers"
        }
      ]
    }
  }
]
